markdown_columns-1.0.2.dist-info/DESCRIPTION.rst
markdown_columns-1.0.2.dist-info/METADATA
markdown_columns-1.0.2.dist-info/RECORD
markdown_columns-1.0.2.dist-info/WHEEL
markdown_columns-1.0.2.dist-info/metadata.json
markdown_columns-1.0.2.dist-info/top_level.txt
md_columns/__init__.py
md_columns/md_columns.py
