Metadata-Version: 2.0
Name: markdown-columns
Version: 1.0.2
Summary: css columns for Python Markdown
Home-page: https://github.com/sander76/markdown-columns
Author: Sander Teunissen
Author-email: UNKNOWN
License: MIT
Platform: UNKNOWN
Classifier: Programming Language :: Python
Classifier: Topic :: Software Development :: Libraries :: Python Modules
Classifier: License :: OSI Approved :: BSD License
Classifier: Operating System :: OS Independent
Classifier: Development Status :: 5 - Production/Stable
Classifier: Intended Audience :: Developers
Classifier: Programming Language :: Python :: 3
